pangeo_fish/__init__.py
pangeo_fish/__main__.py
pangeo_fish/acoustic.py
pangeo_fish/cf.py
pangeo_fish/dataset_utils.py
pangeo_fish/diff.py
pangeo_fish/filters.py
pangeo_fish/functoolz.py
pangeo_fish/grid.py
pangeo_fish/healpy.py
pangeo_fish/helpers.py
pangeo_fish/io.py
pangeo_fish/model.py
pangeo_fish/pdf.py
pangeo_fish/tags.py
pangeo_fish/tracks.py
pangeo_fish/utils.py
pangeo_fish/visualization.py
pangeo_fish/cli/__init__.py
pangeo_fish/cli/cluster.py
pangeo_fish/cli/main.py
pangeo_fish/cli/path.py
pangeo_fish/cli/prepare.py
pangeo_fish/distributions/__init__.py
pangeo_fish/distributions/healpix.py
pangeo_fish/distributions/planar2d.py
pangeo_fish/hmm/__init__.py
pangeo_fish/hmm/decode.py
pangeo_fish/hmm/filter.py
pangeo_fish/hmm/prediction.py
pangeo_fish/hmm/estimator/__init__.py
pangeo_fish/hmm/estimator/cached.py
pangeo_fish/hmm/estimator/eager.py
pangeo_fish/hmm/optimize/__init__.py
pangeo_fish/hmm/optimize/logging.py
pangeo_fish/hmm/optimize/optuna.py
pangeo_fish/hmm/optimize/scipy.py
pangeo_fish/tests/test_acoustic.py
pangeo_fish/tests/test_diff.py
pangeo_fish/tests/test_distributions.py
pangeo_fish/tests/test_estimator.py
pangeo_fish/tests/test_grid.py
pangeo_fish/tests/test_hmm_optimize.py
pangeo_fish/tests/test_io.py
pangeo_fish/tests/test_pdf.py
pangeo_fish/tests/test_tags.py
pangeo_fish/tests/test_tracks.py
pangeo_fish/tests/test_utils.py
pangeo_fish-2025.3.3.dist-info/licenses/LICENSE
pangeo_fish-2025.3.3.dist-info/METADATA
pangeo_fish-2025.3.3.dist-info/WHEEL
pangeo_fish-2025.3.3.dist-info/entry_points.txt
pangeo_fish-2025.3.3.dist-info/top_level.txt
pangeo_fish-2025.3.3.dist-info/RECORD
